{
    "center": { "lat": 48.8632, "lng": 2.3359 },
    "zoom": 12,
    "stations": [
        { "name": "La Défense", "lat": 48.8925, "lng": 2.2381 },
        { "name": "Esplanade de la Défense", "lat": 48.8882, "lng": 2.2503 },
        { "name": "Pont de Neuilly", "lat": 48.8841, "lng": 2.2567 },
        { "name": "Les Sablons", "lat": 48.8815, "lng": 2.2694 },
        { "name": "Porte Maillot", "lat": 48.8786, "lng": 2.2821 },
        { "name": "Argentine", "lat": 48.8756, "lng": 2.2903 },
        { "name": "Charles de Gaulle-Étoile", "lat": 48.8738, "lng": 2.2950 },
        { "name": "George V", "lat": 48.8722, "lng": 2.3003 },
        { "name": "Franklin D. Roosevelt", "lat": 48.8699, "lng": 2.3072 },
        { "name": "Champs-Élysées-Clemenceau", "lat": 48.8663, "lng": 2.3131 },
        { "name": "Concorde", "lat": 48.8655, "lng": 2.3211 },
        { "name": "Tuileries", "lat": 48.8636, "lng": 2.3280 },
        { "name": "Palais Royal-Musée du Louvre", "lat": 48.8625, "lng": 2.3360 },
        { "name": "Louvre-Rivoli", "lat": 48.8618, "lng": 2.3419 },
        { "name": "Châtelet", "lat": 48.8584, "lng": 2.3470 },
        { "name": "Hôtel de Ville", "lat": 48.8574, "lng": 2.3513 },
        { "name": "Saint-Paul", "lat": 48.8555, "lng": 2.3625 },
        { "name": "Bastille", "lat": 48.8532, "lng": 2.3693 },
        { "name": "Gare de Lyon", "lat": 48.8443, "lng": 2.3748 },
        { "name": "Reuilly-Diderot", "lat": 48.8497, "lng": 2.3860 },
        { "name": "Nation", "lat": 48.8483, "lng": 2.3952 },
        { "name": "Porte de Vincennes", "lat": 48.8474, "lng": 2.4063 },
        { "name": "Saint-Mandé", "lat": 48.8446, "lng": 2.4151 },
        { "name": "Bérault", "lat": 48.8420, "lng": 2.4236 },
        { "name": "Château de Vincennes", "lat": 48.8440, "lng": 2.4358 }
    ]
}
  